LICENSE
MANIFEST.in
README.md
setup.py
geograpy2/__init__.py
geograpy2/extraction.py
geograpy2/place.py
geograpy2/placecontext.py
geograpy2.egg-info/PKG-INFO
geograpy2.egg-info/SOURCES.txt
geograpy2.egg-info/dependency_links.txt
geograpy2.egg-info/not-zip-safe
geograpy2.egg-info/requires.txt
geograpy2.egg-info/top_level.txt