Metadata-Version: 1.1
Name: geograpy2
Version: 0.1.0
Summary: Extract countries, regions and cities from a URL or text
Home-page: https://github.com/Corollarium/geograpy2
Author: Corollarium
Author-email: email@corollarium.com
License: MIT
Download-URL: https://github.com/Corollarium/geograpy2
Platform: UNKNOWN
